{"title":"First Look: The Nordest Candonga 2 is a Pinion Smart Shift-Equipped Titanium Gravel Bike","link":"https://velo.outsideonline.com/gravel/gravel-gear/nordest-candonga-2-pinion-smart-shift-titanium-gravel-bike/","date":1729689903000,"content":"<figure><img src=\"https://velo-cdn.outsideonline.com/wp-content/uploads/2024/10/Candonda-2-Ti-006.jpeg?width=1200\" alt=\"First Look: The Nordest Candonga 2 is a Pinion Smart Shift-Equipped Titanium Gravel Bike\" /></figure>\n<p>Nordest Cycles offer up a more affordable option for an electronic shift gearbox-equipped titanium gravel bike, with clearance for 700c x 50mm tires</p>\n<p>Read the full article at <a href=\"https://velo.outsideonline.com/gravel/gravel-gear/nordest-candonga-2-pinion-smart-shift-titanium-gravel-bike/\">First Look: The Nordest Candonga 2 is a Pinion Smart Shift-Equipped Titanium Gravel Bike</a> on <a href=\"https://velo.outsideonline.com\">Velo</a>.</p>","author":"Jessie-May Morgan","siteTitle":"CyclingTips","siteHash":"30feca30fb3902119bf2da6559e7337232527b61c9abe0a00f5d7543c6aa6c84","entryHash":"0c8bf155d1c9b690408ec138687ba5d9b17fffa411049753c7799182dd78c16b","category":"Cycling"}