{"title":"Ouch-1 Platform Hinge for Omnium Cargo","link":"https://theradavist.com/ouch-1-platform-hinge-omnium-cargo/","date":1715263434000,"content":"<p>One of the bummers about front loading, platform cargo bikes is how much space they take up. The <a href=\"https://damgood.bike/products/ouch-1-omnium-utter-cargo-hinge\" target=\"_blank\">Ouch-1</a> ($115) looks to alleviate that with a folding platform hinge. This video explains how it works. Check out more at <a href=\"https://damgood.bike/products/ouch-1-omnium-utter-cargo-hinge\" target=\"_blank\">Damgood.bike</a>.</p>\n<p>The post <a href=\"https://theradavist.com/ouch-1-platform-hinge-omnium-cargo/\">Ouch-1 Platform Hinge for Omnium Cargo</a> appeared first on <a href=\"https://theradavist.com\">The Radavist</a>.</p>","author":"John Watson","siteTitle":"The Radavist","siteHash":"96eb481d8084f04a4602bac57874ba717baf56b758f45547b5caf2312da766ef","entryHash":"1ca6b59a33cc71b2b7620386101f7ad4bbbbdfd87ddc2493b045b46d6957f0c8","category":"Cycling"}