{"title":"Jonas Vingegaard Loses Key Wingman for Tour de France Showdown with Tadej Pogačar","link":"https://velo.outsideonline.com/road/road-racing/vingegaard-loses-key-wingman-for-tour-de-france/","date":1748097054000,"content":"<figure><img src=\"https://velo-cdn.outsideonline.com/wp-content/uploads/2025/05/GettyImages-2161012174.jpg?width=1200\" alt=\"Jonas Vingegaard Loses Key Wingman for Tour de France Showdown with Tadej Pogačar\" /></figure>\n<p>Visma-Lease a Bike’s curse of injury and illness continues as all-terrain French ace Laporte ruled out with ongoing, long-term sickness.</p>\n<p>Read the full article at <a href=\"https://velo.outsideonline.com/road/road-racing/vingegaard-loses-key-wingman-for-tour-de-france/\">Jonas Vingegaard Loses Key Wingman for Tour de France Showdown with Tadej Pogačar</a> on <a href=\"https://velo.outsideonline.com\">Velo</a>.</p>","author":"Jim Cotton","siteTitle":"CyclingTips","siteHash":"30feca30fb3902119bf2da6559e7337232527b61c9abe0a00f5d7543c6aa6c84","entryHash":"4c7f3c10cb518f660e7af92f358896f36bf1f3796fffe4a5525fb7e4d578109b","category":"Cycling"}