{"title":"MarkItDown: Python Tool for Converting Files and Office Documents to Markdown","link":"https://github.com/microsoft/markitdown","date":1734133234000,"content":"\n<p>Nifty new convert-to-Markdown library from a small indie development shop named Microsoft:</p>\n\n<blockquote>\n  <p>The MarkItDown library is a utility tool for converting various\nfiles to Markdown (e.g., for indexing, text analysis, etc.)</p>\n\n<p>It presently supports:</p>\n\n<ul>\n<li>PDF (.pdf)</li>\n<li>PowerPoint (.pptx)</li>\n<li>Word (.docx)</li>\n<li>Excel (.xlsx)</li>\n<li>Images (EXIF metadata, and OCR)</li>\n<li>Audio (EXIF metadata, and speech transcription)</li>\n<li>HTML (special handling of Wikipedia, etc.)</li>\n<li>Various other text-based formats (csv, json, xml, etc.)</li>\n</ul>\n\n<p>The API is simple:</p>\n\n<p>from markitdown import MarkItDown</p>\n\n<p>markitdown = MarkItDown()\n   result = markitdown.convert(“test.xlsx”)\n   print(result.text_content)</p>\n</blockquote>\n\n<p><a href=\"https://x.com/kepano/status/1867664671446381017\">Via Stephan Ango</a> (CEO of the excellent, popular Markdown writing and note-taking app <a href=\"https://obsidian.md/?df\">Obsidian</a>), who also points out that <a href=\"https://x.com/kepano/status/1813975676875362795\">Google Docs added Markdown export</a> a few months ago. I’ve never used Google Docs other than to read documents created by others, but MarkItDown seems like a library I might make great use of. “MarkItDown” is even a great name. What a world.</p>\n\n<p>Not bad for a <a href=\"https://daringfireball.net/2004/03/introducing_markdown\">20-year-old syntax</a>.</p>\n\n<div>\n<a href=\"https://daringfireball.net/linked/2024/12/13/markitdown\"> ★ </a>\n</div>\n\n\t","author":"John Gruber","siteTitle":"Daring Fireball","siteHash":"fc569638025dadf22a867470f8215f38855cf50e975782a6c989909474292a36","entryHash":"5eb303468ad3160ebffbb1a2b69b0b0e310f01dcbf11673e7ed751efc866d4bb","category":"Tech"}