{"title":"‘Far From Ideal’: Kuss Crashes a Second Time at Burgos as Massive Pileup Sees Geoghegan Hart, August DNF","link":"https://velo.outsideonline.com/road/road-racing/massive-burgos-pileup-sees-geoghegan-hart-crash-out/","date":1723014550000,"content":"<figure><img src=\"https://velo-cdn.outsideonline.com/wp-content/uploads/2024/08/GettyImages-2165361703.jpg?width=1200\" alt=\"'Far From Ideal': Kuss Crashes a Second Time at Burgos as Massive Pileup Sees Geoghegan Hart, August DNF\" /></figure>\n<p>Sepp Kuss crashes for second day in a row as several riders slammed to the ground with about 35km to go in the second stage of the Vuelta a España warmup race.</p>\n<p>Read the full article at <a href=\"https://velo.outsideonline.com/road/road-racing/massive-burgos-pileup-sees-geoghegan-hart-crash-out/\">‘Far From Ideal’: Kuss Crashes a Second Time at Burgos as Massive Pileup Sees Geoghegan Hart, August DNF</a> on <a href=\"https://velo.outsideonline.com\">Velo</a>.</p>","author":"ahood","siteTitle":"CyclingTips","siteHash":"30feca30fb3902119bf2da6559e7337232527b61c9abe0a00f5d7543c6aa6c84","entryHash":"67a512debf12993c9e1baa8569daf9109070f5bdb9082f01fb8ce9b4ad66712f","category":"Cycling"}