{"title":"VIDEO: Hudski Bikes Follow Cam Kite","link":"https://theradavist.com/video-hudski-bikes-follow-cam-kite/","date":1711980291000,"content":"<p>Next up with some April Fools’ foolery is from <a href=\"https://hudskibikes.com/\" target=\"_blank\">Hudski Bikes</a>… We’ve all thought about it, but has anyone tried it? A follow cam kite, or what we’re calling the “FCK it” for short. No batteries needed, no fancy drone piloting necessary, just traditional Japanese kit making and an iPhone. Huck it and FCK it!</p>\n<p>The post <a href=\"https://theradavist.com/video-hudski-bikes-follow-cam-kite/\">VIDEO: Hudski Bikes Follow Cam Kite</a> appeared first on <a href=\"https://theradavist.com\">The Radavist</a>.</p>","author":"John Watson","siteTitle":"The Radavist","siteHash":"96eb481d8084f04a4602bac57874ba717baf56b758f45547b5caf2312da766ef","entryHash":"6f3f7ea435cdfcd9ab936b35a3f69cfb0726d51c336de00ace0df93fd4f8381d","category":"Cycling"}