{"title":"Trump has “a little problem” with Apple’s plan to ship iPhones from India","link":"https://arstechnica.com/tech-policy/2025/05/trump-has-a-little-problem-with-apples-plan-to-ship-iphones-from-india/","date":1747318486000,"content":"<p>Donald Trump has hit out at Apple’s plans to produce more iPhones in India as a way of avoiding US tariffs on Chinese-made goods, as he continues to push the tech group to manufacture its best-selling device in America.</p>\n<p>Speaking in Qatar on the latest leg of his Middle East tour, the US president said he had “a little problem with Tim Cook yesterday” after the Apple chief executive confirmed last week that Indian factories would supply the “majority” of iPhones sold in the US in the coming months.</p>\n<p>The Financial Times previously reported that Apple planned to source from India all of the more than 60 million iPhones sold annually in the US by the end of next year.</p><p><a href=\"https://arstechnica.com/tech-policy/2025/05/trump-has-a-little-problem-with-apples-plan-to-ship-iphones-from-india/\">Read full article</a></p>\n<p><a href=\"https://arstechnica.com/tech-policy/2025/05/trump-has-a-little-problem-with-apples-plan-to-ship-iphones-from-india/#comments\">Comments</a></p>","author":"Tim Bradshaw and John Reed, Financial Times","siteTitle":"Ars Technica","siteHash":"5b0ddf6e8923e49262a7894cfd77962733e43fbcc565a103b48373820b310636","entryHash":"724cbe6ce0e46c34329970061599e63e76d7b6b4ddc7068713f8ae51775e21b8","category":"Tech"}