{"title":"ข่าวลือรอบล่าสุด iPad Pro / iPad Air รุ่นใหม่ กำหนดเปิดตัวพฤษภาคมนี้","link":"https://www.blognone.com/node/138959","date":1711674864000,"content":"<div><div><div><p>Mark Gurman แห่ง Bloomberg คนเดิม มีข้อมูลล่าสุดของ iPad Pro รุ่นใหม่ คราวนี้เขาอ้างแหล่งข่าวระบุว่า iPad Pro ใหม่กำหนดเปิดตัวช่วงต้นเดือนพฤษภาคม โดยมาพร้อม iPad Air รุ่นใหม่ด้วย</p>\n<p>ก่อนหน้านี้ก็ Gurman เอง ที่เคยบอกว่า iPad รุ่นใหม่จะออกมาช่วง<a href=\"https://www.blognone.com/node/138620\">มีนาคม-เมษายน</a> ซึ่งจะไม่มีการจัดงานแถลงข่าวเปิดตัว เช่นเดียวกับ <a href=\"https://www.blognone.com/node/138529\">MacBook Air M3</a></p>\n<p>iPad Pro รุ่นใหม่ มีสเป็กตามข่าวลือที่ออกมาคือ ชิป M3, จอ OLED, Magic Keyboard รุ่นใหม่ มี Trackpad ใหญ่ขึ้น ส่วน iPad Air จะออกเป็นสองรุ่นย่อย เพิ่มขนาดหน้าจอ 12.9 นิ้ว อัปเกรดทั้งสองรุ่นเป็นชิป M2</p>\n<p>ที่มา: <a href=\"https://www.bloomberg.com/news/articles/2024-03-28/when-is-the-new-ipad-pro-ipad-air-coming-out-apple-plans-early-may-launch\">Bloomberg</a></p>\n<p><img src=\"https://www.blognone.com/sites/default/files/externals/50664e4d56925665a7bbc00a43c7a848.jpg\" /></p>\n</div></div></div><div><div>Topics: </div><div><div><a href=\"/topics/apple\">Apple</a></div><div><a href=\"/topics/rumors\">Rumors</a></div><div><a href=\"/topics/ipad-pro\">iPad Pro</a></div><div><a href=\"/topics/ipad-air\">iPad Air</a></div></div></div>","author":"arjin","siteTitle":"Blognone","siteHash":"ededadcf18490b3937e7dd89ebe8c00dc129addbdf1ebe4aff1f458146693da0","entryHash":"8efccc08242034428c181fb10843beb7abc094e76f3b109078ba050ef9a1059a","category":"Thai"}