{"title":"Miguel’s End of Summer Picks","link":"https://theradavist.com/miguels-end-of-summer-picks/","date":1725445087000,"content":"<p>Every year, the team at The Radavist shares their favorite products from their summer riding season, and this year, <a href=\"https://theradavist.com/tag/race-metal/\" target=\"_blank\">Miguel</a> shares his favorite on our YouTube channel. What are some of your favorite products you’ve been using this summer?</p>\n<p><strong>Please, if you enjoy these videos, hit the subscribe button below!</strong></p>\n<p> </p>\n<p></p>\n<div></div>\n<p> </p>\n<p>The post <a href=\"https://theradavist.com/miguels-end-of-summer-picks/\">Miguel’s End of Summer Picks</a> appeared first on <a href=\"https://theradavist.com\">The Radavist</a>.</p>","author":"John Watson","siteTitle":"The Radavist","siteHash":"96eb481d8084f04a4602bac57874ba717baf56b758f45547b5caf2312da766ef","entryHash":"928a990028c9c01c28ff500a8363179acaa1218fb797102ca09187401d4197d2","category":"Cycling"}