{"title":"Cavendish, Froome, Roglič Headline First Round of Curious Off-Season Criteriums","link":"https://velo.outsideonline.com/news/cavendish-froome-roglic-headline-saitama-criterium/","date":1730464488000,"content":"<figure><img src=\"https://velo-cdn.outsideonline.com/wp-content/uploads/2024/11/GettyImages-1439160506.jpg?width=1200\" alt=\"Cavendish, Froome, Roglič Headline First Round of Curious Off-Season Criteriums\" /></figure>\n<p>You know it's off-season when the year-end Asian exhibitions begin. Expect kimonos, martial arts, and very little racing.</p>\n<p>Read the full article at <a href=\"https://velo.outsideonline.com/news/cavendish-froome-roglic-headline-saitama-criterium/\">Cavendish, Froome, Roglič Headline First Round of Curious Off-Season Criteriums</a> on <a href=\"https://velo.outsideonline.com\">Velo</a>.</p>","author":"Jim Cotton","siteTitle":"CyclingTips","siteHash":"30feca30fb3902119bf2da6559e7337232527b61c9abe0a00f5d7543c6aa6c84","entryHash":"9befc5be014738fdcef56fecff27cb80421cc3a5a31fbc2d6184648fa2a917da","category":"Cycling"}