{"title":"Live Updates Giro d’Italia Stage 3: Breakaway Clear but Losing Time on Last Day in Albania","link":"https://velo.outsideonline.com/road/road-racing/giro-ditalia/giro-ditalia-stage-3-2025-live-updates/","date":1746958323000,"content":"<figure><img src=\"https://velo-cdn.outsideonline.com/wp-content/uploads/2025/05/GettyImages-2214515156.jpg?width=1200\" alt=\"Live Updates Giro d'Italia Stage 3: Breakaway Clear but Losing Time on Last Day in Albania\" /></figure>\n<p>All the latest updates, breaking news and results from the year's first grand tour.</p>\n<p>Read the full article at <a href=\"https://velo.outsideonline.com/road/road-racing/giro-ditalia/giro-ditalia-stage-3-2025-live-updates/\">Live Updates Giro d’Italia Stage 3: Breakaway Clear but Losing Time on Last Day in Albania</a> on <a href=\"https://velo.outsideonline.com\">Velo</a>.</p>","author":"Will Tracy","siteTitle":"CyclingTips","siteHash":"30feca30fb3902119bf2da6559e7337232527b61c9abe0a00f5d7543c6aa6c84","entryHash":"c2911970421aa55a819acf65937d9524eea91a3c7093e59972f587cbbc56f686","category":"Cycling"}