{"title":"ASUS เปิดตัว NUC 15 Pro อัปเกรดสเป็ก ส่วน NUC 14 Pro AI+ มีลูกเล่นหน้าจอ E-ink ปรับแต่งได้","link":"https://www.blognone.com/node/144070","date":1736656376000,"content":"<div><div><div><p>ASUS เปิดตัวสินค้าตระกูล NUC ชุดใหม่ ซึ่งมาพร้อมจุดขายหลักคือการรองรับ AI รายละเอียดดังนี้</p>\n<ul>\n<li><strong>NUC 15 Pro</strong> ซีพียู Intel Core Ultra 7 ซีรีส์ 2, Wi-Fi 7, บลูทูธ 5.4</li>\n<li><strong>NUC 15 Pro+</strong> ซีพียู Intel Core Ultra 9 ซีรีส์ 2 สูงสุด 99 TOPS รองรับการประมวลผล AI ที่มากขึ้น</li>\n<li><strong>NUC 14 Pro AI+</strong> รุ่นอัปเกรดของ <a href=\"https://www.blognone.com/node/143776\">NUC 14 Pro AI</a> มีปุ่มลัดเรียก Copilot ส่วนด้านบนเพิ่มจอ E-ink ปรับแต่งการแสดงผลได้</li>\n</ul>\n<p>นอกจากนี้ ASUS ยังเปิดตัว <strong>ExpertCenter PN54</strong> มินีพีซีที่ใช้ซีพียู Ryzen AI 7 350 รองรับ NPU 45 TOPS สำหรับการใช้ AI ทั่วไปตั้งแต่ครีเอเตอร์จนถึงเล่นเกม</p>\n<p>ที่มา: <a href=\"https://press.asus.com/news/press-releases/asus-ces-2025-ai-copilot-pc-lineup/\">ASUS</a></p>\n<p><img alt=\"No Description\" src=\"https://www.blognone.com/sites/default/files/externals/c4f756407b81e216ed830936293c11a7.jpeg\" /></p>\n</div></div></div><div><div>Topics: </div><div><div><a href=\"/topics/asus\">ASUS</a></div><div><a href=\"/topics/nuc\">NUC</a></div><div><a href=\"/topics/mini-pc\">Mini PC</a></div><div><a href=\"/topics/hardware\">Hardware</a></div></div></div>","author":"arjin","siteTitle":"Blognone","siteHash":"ededadcf18490b3937e7dd89ebe8c00dc129addbdf1ebe4aff1f458146693da0","entryHash":"cf62f0cd7a5e9a992d1bacb5efb18a0a04d29a2f6ae35515459b9e7eee3a75be","category":"Thai"}