{"title":"Politt and His Celebrity Toilet Trip, Van Aert’s Cartwheeling Crash: Footage You Missed at the Olympic Road Race","link":"https://velo.outsideonline.com/olympics/politt-treated-to-vip-send-off-after-olympic-toilet-trip/","date":1722759401000,"content":"<figure><img src=\"https://velo-cdn.outsideonline.com/wp-content/uploads/2024/08/GettyImages-2164686683.jpg?width=1200\" alt=\"Politt and His Celebrity Toilet Trip, Van Aert’s Cartwheeling Crash: Footage You Missed at the Olympic Road Race\" /></figure>\n<p>Videos emerge from wild Olympic road race of Politt seeing VIP treatment after an emergency pee stop, Van Aert flipping over his bars in dramatic crash.</p>\n<p>Read the full article at <a href=\"https://velo.outsideonline.com/olympics/politt-treated-to-vip-send-off-after-olympic-toilet-trip/\">Politt and His Celebrity Toilet Trip, Van Aert’s Cartwheeling Crash: Footage You Missed at the Olympic Road Race</a> on <a href=\"https://velo.outsideonline.com\">Velo</a>.</p>","author":"Jim Cotton","siteTitle":"CyclingTips","siteHash":"30feca30fb3902119bf2da6559e7337232527b61c9abe0a00f5d7543c6aa6c84","entryHash":"e8c5f13f9c11c5f24df5859976c3905382c51938a3cc7165e9d3d5e3c347de2a","category":"Cycling"}