{"title":"Excel เพิ่ม 3 ฟังก์ชันใหม่ เรียกใช้งาน Regex ได้โดยตรง","link":"https://www.blognone.com/node/139874","date":1716285264000,"content":"<div><div><div><p>ไมโครซอฟท์ประกาศเพิ่มฟังก์ชันใหม่ 3 รายการ สำหรับ Excel ซึ่งทั้งหมดเป็นฟังก์ชัน Regular Expressions (regex) โดยมีผลกับผู้ใช้งานกลุ่ม Microsoft 365 Insider ก่อน</p>\n<p>ที่ผ่านมาผู้ใช้ Excel มีวิธีต่าง ๆ ในการใช้งาน regex บน Excel แต่จากนี้จะสามารถใช้ฟังก์ชันโดยตรงได้แล้ว ซึ่งมีดังนี้</p>\n<ul>\n<li><strong>REGEXTEST</strong>: ใช้ตรวจสอบข้อความ text ว่า match หรือไม่ (return TRUE หรือ FALSE)</li>\n<li><strong>REGEXEXTRACT</strong>: ใช้ดึงส่วนของข้อความทั้งหมดที่ตรงตามเงื่อนไข (return ค่าแรก, ค่าทั้งหมด หรือแยกตามกลุ่ม)</li>\n<li><strong>REGEXREPLACE</strong>: ค้นหาข้อความส่วนที่ตรงตามเงื่อนไข และแทนที่ตามที่กำหนด</li>\n</ul>\n<p>ไมโครซอฟท์บอกว่า regex จะเพิ่มเป็นทางเลือกใช้งานในฟังก์ชัน XLOOKUP และ XMATCH ที่เป็น match mode ด้วยในอนาคต ทั้งนี้ไมโครซอฟท์ยังบอกว่าทั้ง 3 ฟังก์ชันยังอยู่ในสถานะพรีวิวและอาจมีการปรับปรุงแก้ไขได้ จึงไม่แนะนำให้ทดสอบใช้งานกับไฟล์ข้อมูลที่สำคัญ</p>\n<p>ที่มา: <a href=\"https://insider.microsoft365.com/en-us/blog/new-regular-expression-regex-functions-in-excel\">ไมโครซอฟท์</a></p>\n<p><img alt=\"No Description\" src=\"https://www.blognone.com/sites/default/files/externals/e9154b531d8717d597468b4a4180dbdd.jpg\" /></p>\n<p>REGEXTEST</p>\n<p><img alt=\"No Description\" src=\"https://www.blognone.com/sites/default/files/externals/00ba87822118a3837fe1677955035c22.png\" /></p>\n<p>REGEXEXTRACT</p>\n<p><img alt=\"No Description\" src=\"https://www.blognone.com/sites/default/files/externals/0dc9b1e976705ea849b2f33eb4acdfae.png\" /></p>\n<p>REGEXREPLACE</p>\n<p><img alt=\"No Description\" src=\"https://www.blognone.com/sites/default/files/externals/a115c6635becae6ee88dcdfe51188e41.png\" /></p>\n</div></div></div><div><div>Topics: </div><div><div><a href=\"/topics/excel\">Excel</a></div><div><a href=\"/topics/microsoft-365\">Microsoft 365</a></div></div></div>","author":"arjin","siteTitle":"Blognone","siteHash":"ededadcf18490b3937e7dd89ebe8c00dc129addbdf1ebe4aff1f458146693da0","entryHash":"fc548926b14bbb0392eec9f1563e1654824893fb774ceb0eed4444c8b098d83a","category":"Thai"}